[
	{
		"id": {
			"opaque_id": "jarek1234",
			"idp": "http://localhost:20080"
		},
		"username": "jarek",
		"secret": "jarekpass",
		"mail": "jarek@ailleron.com",
		"display_name": "Jarek",
		"groups": ["sailing-lovers", "violin-haters", "physics-lovers"]
	},
	{
		"id": {
			"opaque_id": "mateusz5678",
			"idp": "http://localhost:20080"
		},
		"username": "mateusz",
		"secret": "mateuszpass",
		"mail": "mateusz@ailleron.com",
		"display_name": "Mateusz",
		"groups": ["radium-lovers", "polonium-lovers", "physics-lovers"]
	},
	{
		"id": {
			"opaque_id": "dawid9876",
			"idp": "http://localhost:20080"
		},
		"username": "dawid",
		"secret": "dawidpass",
		"mail": "dawid@ailleron.com",
		"display_name": "Dawid",
		"groups": ["quantum-lovers", "philosophy-haters", "physics-lovers"]
	}
]
